rorclient/__init__.py
rorclient/async_client.py
rorclient/base.py
rorclient/client.py
rorclient/config.py
rorclient/utils.py
rorclient/models/__init__.py
rorclient/models/admin.py
rorclient/models/external_id.py
rorclient/models/institution.py
rorclient/models/link.py
rorclient/models/location.py
rorclient/models/name.py
rorclient/models/relationship.py
rorclient/models/search.py
rorclient-0.1.0.dist-info/LICENSE
rorclient-0.1.0.dist-info/METADATA
rorclient-0.1.0.dist-info/WHEEL
rorclient-0.1.0.dist-info/top_level.txt
rorclient-0.1.0.dist-info/RECORD
