Metadata-Version: 2.2
Name: rorclient
Version: 0.1.0
Summary: A Python client for interacting with the ROR API
Author-email: Alexander Dernild <alex@dernild.dk>
Project-URL: Homepage, https://github.com/ADernild/RORClient
Project-URL: Bug Tracker, https://github.com/ADernild/RORClient/issues
Classifier: Development Status :: 3 - Alpha
Classifier: Intended Audience :: Developers
Classifier: Topic :: Software Development :: Libraries :: Python Modules
Classifier: Programming Language :: Python :: 3
Classifier: Programming Language :: Python :: 3.11
Classifier: Programming Language :: Python :: 3.12
Classifier: Programming Language :: Python :: 3.13
Classifier: License :: OSI Approved :: MIT License
Classifier: Operating System :: OS Independent
Requires-Python: >=3.11
License-File: LICENSE
Requires-Dist: httpx<1.0,>=0.28.1
Requires-Dist: pydantic<3.0,>=2.10.6
Requires-Dist: backoff<3.0,>=2.2.1
Provides-Extra: dev
Requires-Dist: ruff<1.0,>=0.1.14; extra == "dev"
Requires-Dist: pytest>=8.3.4; extra == "dev"
Requires-Dist: pytest-mock>=3.14.0; extra == "dev"
Requires-Dist: pytest-asyncio>=0.25.3; extra == "dev"
Provides-Extra: docs
Requires-Dist: sphinx<9.0,>=8.2.1; extra == "docs"
Requires-Dist: sphinx-autobuild==2024.10.3; extra == "docs"
Requires-Dist: sphinx-autodoc-typehints>=3.1.0; extra == "docs"
Requires-Dist: sphinx-book-theme>=1.1.4; extra == "docs"
